README.txt
pyproject.toml
root_painter_trainer.egg-info/PKG-INFO
root_painter_trainer.egg-info/SOURCES.txt
root_painter_trainer.egg-info/dependency_links.txt
root_painter_trainer.egg-info/entry_points.txt
root_painter_trainer.egg-info/requires.txt
root_painter_trainer.egg-info/top_level.txt
src/__init__.py
src/datasets.py
src/elastic.py
src/file_utils.py
src/im_utils.py
src/loss.py
src/main.py
src/metrics.py
src/model_utils.py
src/startup.py
src/trainer.py
src/unet.py
src/multi_epoch/multi_epoch_loader.py
tests/test_loss.py
tests/test_unet.py
tests/test_utils.py